knotter/__init__.py
knotter/knitter.py
knotter/server.py
knotter/tda.py
knotter/mapper/__init__.py
knotter/mapper/clustering.py
knotter/mapper/covering.py
knotter/mapper/lense.py
knotter/static/index.html
knotter/static/bower_components/d3/d3.js
knotter/static/bower_components/d3/d3.min.js
knotter/static/bower_components/d3/package.js
knotter/static/bower_components/font-roboto/roboto.html
knotter/static/bower_components/google-apis/google-apis.html
knotter/static/bower_components/google-apis/google-client-loader.html
knotter/static/bower_components/google-apis/google-js-api.html
knotter/static/bower_components/google-apis/google-legacy-loader.html
knotter/static/bower_components/google-apis/google-maps-api.html
knotter/static/bower_components/google-apis/google-plusone-api.html
knotter/static/bower_components/google-apis/google-realtime-api.html
knotter/static/bower_components/google-apis/google-youtube-api.html
knotter/static/bower_components/google-apis/index.html
knotter/static/bower_components/google-apis/demo/index.html
knotter/static/bower_components/google-map/google-map-directions.html
knotter/static/bower_components/google-map/google-map-marker.html
knotter/static/bower_components/google-map/google-map-search.html
knotter/static/bower_components/google-map/google-map.html
knotter/static/bower_components/google-map/index.html
knotter/static/bower_components/google-map/metadata.html
knotter/static/bower_components/google-map/demo/index.html
knotter/static/bower_components/google-map/demo/test.html
knotter/static/bower_components/iron-a11y-announcer/index.html
knotter/static/bower_components/iron-a11y-announcer/iron-a11y-announcer.html
knotter/static/bower_components/iron-a11y-announcer/demo/index.html
knotter/static/bower_components/iron-a11y-announcer/demo/x-announces.html
knotter/static/bower_components/iron-a11y-announcer/test/index.html
knotter/static/bower_components/iron-a11y-announcer/test/iron-a11y-announcer.html
knotter-0.3.3.dist-info/LICENSE
knotter-0.3.3.dist-info/METADATA
knotter-0.3.3.dist-info/WHEEL
knotter-0.3.3.dist-info/entry_points.txt
knotter-0.3.3.dist-info/top_level.txt
knotter-0.3.3.dist-info/RECORD
